{
  "experiment": "Day League personality \u2014 owl",
  "started": "2026-07-09",
  "account": {
    "currency": "USD",
    "starting_balance": 5000.0,
    "balance": 5060.4,
    "open_risk_R": 0
  },
  "rules": {
    "risk_per_trade_pct": 1.0,
    "cost_per_trade_R": 0.05,
    "max_open_positions": 2,
    "max_open_risk_R": 2.0,
    "max_entries_per_day": 4,
    "setups_allowed": [
      "orb_long",
      "vwap_pullback"
    ],
    "style": "day trading, 5-minute bars, replayed after the close",
    "verdict_metric": "expectancy_R_after_costs",
    "verdict_sample": "100 trades or 6 months",
    "personality": "owl"
  },
  "watchlist": [
    "SPY",
    "QQQ",
    "NVDA",
    "AAPL",
    "MSFT",
    "AMD",
    "TSLA",
    "META",
    "AMZN",
    "GOOGL"
  ],
  "stats": {
    "trades_closed": 4,
    "wins": 2,
    "losses": 2,
    "win_rate_pct": 50.0,
    "expectancy_R": 0.281,
    "total_R": 1.125,
    "max_drawdown_pct": 1.01
  },
  "open_trades": [],
  "pending_orders": [],
  "closed_trades": [
    {
      "id": "2026-07-09-AMD-4",
      "ticker": "AMD",
      "setup": "vwap_pullback",
      "entry": 551.72,
      "stop": 546.1,
      "target": 562.96,
      "shares": 8,
      "risk_usd": 44.960000000000036,
      "opened": "2026-07-09",
      "entry_bar": 11,
      "note": "Held above VWAP then first pullback into it (bar 10); long on reclaim of 551.71, stop under the dip 546.65.",
      "exit": 546.1,
      "closed": "2026-07-09",
      "reason": "stop",
      "r_multiple": -1.05,
      "pnl_usd": -47.21,
      "balance_after": 4952.79
    },
    {
      "id": "2026-07-09-MSFT-5",
      "ticker": "MSFT",
      "setup": "vwap_pullback",
      "entry": 377.61,
      "stop": 375.91,
      "target": 381.01,
      "shares": 29,
      "risk_usd": 49.29999999999967,
      "opened": "2026-07-09",
      "entry_bar": 15,
      "note": "Held above VWAP then first pullback into it (bar 14); long on reclaim of 377.60, stop under the dip 376.29.",
      "exit": 381.01,
      "closed": "2026-07-09",
      "reason": "target",
      "r_multiple": 1.95,
      "pnl_usd": 96.13,
      "balance_after": 5048.92
    },
    {
      "id": "2026-07-10-META-5",
      "ticker": "META",
      "setup": "vwap_pullback",
      "entry": 670.54,
      "stop": 666.48,
      "target": 678.66,
      "shares": 12,
      "risk_usd": 48.719999999999345,
      "opened": "2026-07-10",
      "entry_bar": 20,
      "note": "Held above VWAP then first pullback into it (bar 18); long on reclaim of 670.53, stop under the dip 667.15.",
      "exit": 666.48,
      "closed": "2026-07-10",
      "reason": "stop",
      "r_multiple": -1.05,
      "pnl_usd": -51.16,
      "balance_after": 4997.76
    },
    {
      "id": "2026-07-10-NVDA-4",
      "ticker": "NVDA",
      "setup": "vwap_pullback",
      "entry": 207.85,
      "stop": 205.51,
      "target": 212.53,
      "shares": 21,
      "risk_usd": 49.14000000000007,
      "opened": "2026-07-10",
      "entry_bar": 21,
      "note": "Held above VWAP then first pullback into it (bar 12); long on reclaim of 207.84, stop under the dip 205.72.",
      "exit": 210.95,
      "closed": "2026-07-10",
      "reason": "eod_flat",
      "r_multiple": 1.275,
      "pnl_usd": 62.64,
      "balance_after": 5060.4
    }
  ],
  "sessions": [
    {
      "date": "2026-07-09",
      "trades": [
        "2026-07-09-AMD-4",
        "2026-07-09-MSFT-5"
      ],
      "realized_R": 0.9,
      "actions": "AMD stop -1.05R; MSFT target +1.95R",
      "personality": "owl"
    },
    {
      "date": "2026-07-10",
      "trades": [
        "2026-07-10-META-5",
        "2026-07-10-NVDA-4"
      ],
      "realized_R": 0.225,
      "actions": "META stop -1.05R; NVDA eod_flat +1.27R",
      "personality": "owl"
    },
    {
      "date": "2026-07-13",
      "trades": [],
      "realized_R": 0,
      "actions": "No trades \u2014 this personality found nothing worth doing.",
      "personality": "owl"
    }
  ],
  "skipped_candidates": []
}